planformcreator2/icons/PC2.ico
planformcreator2/icons/PC2_ico.pdn
planformcreator2/PC2_ico.ico
planformcreator2/__init__.py
planformcreator2/__main__.py
planformcreator2/app.py
planformcreator2/app_model.py
planformcreator2/app_modes.py
planformcreator2/resources.py
planformcreator2/model/VLM.py
planformcreator2/model/VLM_wing.py
planformcreator2/model/__init__.py
planformcreator2/model/wing.py
planformcreator2/model/wing_exports.py
planformcreator2/ui/__init__.py
planformcreator2/ui/pc2_artists.py
planformcreator2/ui/pc2_diagrams.py
planformcreator2/ui/pc2_dialogs.py
planformcreator2/ui/pc2_panels.py
planformcreator2/templates/ASW_17.png
planformcreator2/templates/Amokka.pc2
planformcreator2/templates/Bow.pc2
planformcreator2/templates/Elliptical.pc2
planformcreator2/templates/F3B_F3F.pc2
planformcreator2/templates/Scale_Glider.pc2
planformcreator2/templates/Spitfire.png
planformcreator2/templates/Trapezoid.pc2
planformcreator2-4.0.1.dist-info/METADATA
planformcreator2-4.0.1.dist-info/WHEEL
planformcreator2-4.0.1.dist-info/entry_points.txt
planformcreator2-4.0.1.dist-info/licenses/LICENSE
planformcreator2-4.0.1.dist-info/RECORD
