Metadata-Version: 2.4
Name: planformcreator2
Version: 4.0.1
Summary: Design a wing planform
Project-URL: Homepage, https://github.com/jxjo/PlanformCreator2
Project-URL: Issues, https://github.com/jxjo/PlanformCreator2/issues
Author-email: Jochen Guenzel <jochen@jxjo.de>
License-Expression: MIT
License-File: LICENSE
Classifier: Intended Audience :: End Users/Desktop
Classifier: Operating System :: OS Independent
Classifier: Programming Language :: Python :: 3.12
Classifier: Programming Language :: Python :: 3.13
Requires-Python: >=3.12
Requires-Dist: airfoileditor>=4.2.3
Requires-Dist: ezdxf>=1.4.0
